fbgs/__init__.py
fbgs/__main__.py
fbgs/datatypes.py
fbgs/exceptions.py
fbgs/scraper.py
fbgs/utils.py
fbgs-1.0.0.dist-info/LICENSE
fbgs-1.0.0.dist-info/METADATA
fbgs-1.0.0.dist-info/WHEEL
fbgs-1.0.0.dist-info/top_level.txt
fbgs-1.0.0.dist-info/RECORD
