Metadata-Version: 2.1
Name: fbgs
Version: 1.0.0
Summary: Python and selenium based (mobile) Facebook groups scraper, independent of obfuscated css selectors.
Home-page: https://github.com/lesander/facebook-group-scraper
License: UNKNOWN
Platform: UNKNOWN
Classifier: Programming Language :: Python :: 3
Classifier: License :: OSI Approved :: MIT License
Classifier: Operating System :: OS Independent
Requires-Python: >=3.6
